CHANGELOG.rst
MANIFEST.in
README.rst
setup.py
check_docking/__init__.py
check_docking/inspect.py
check_docking/middleware.py
check_docking.egg-info/PKG-INFO
check_docking.egg-info/SOURCES.txt
check_docking.egg-info/dependency_links.txt
check_docking.egg-info/requires.txt
check_docking.egg-info/top_level.txt
check_docking.egg-info/zip-safe
check_docking/management/__init__.py
check_docking/management/commands/__init__.py
check_docking/management/commands/inspectprofile.py
check_docking/stored/__init__.py
check_docking/stored/django/__init__.py
check_docking/stored/django/admin.py
check_docking/stored/django/models.py
check_docking/stored/django/tests.py
check_docking/stored/django/views.py
check_docking/stored/django/locale/zh_CN/LC_MESSAGES/django.mo
check_docking/stored/django/locale/zh_CN/LC_MESSAGES/django.po
check_docking/utility/__init__.py
check_docking/utility/exports.py
check_docking/utility/imports.py
check_docking/utility/urls_conf.py
check_docking/utility/urls_data.py
project_demo/manage.py
project_demo/demo/__init__.py
project_demo/demo/common.py
project_demo/demo/demo.py
project_demo/demo/urls.py
project_demo/demo/views.py
project_demo/project/__init__.py
project_demo/project/check_config.py
project_demo/project/settings.py
project_demo/project/urls.py
project_demo/project/wsgi.py